README.md
setup.py
almltools.egg-info/PKG-INFO
almltools.egg-info/SOURCES.txt
almltools.egg-info/dependency_links.txt
almltools.egg-info/requires.txt
almltools.egg-info/top_level.txt
almltools/core/__init__.py
almltools/core/core.py