Metadata-Version: 1.2
Name: almltools
Version: 1.0.0
Summary: Alistair McMasters Machine Learning ToolKit
Home-page: https://github.com/alimcmaster1/al-ml-tools
Author: alistair
Author-email: alimcmaster1@gmail.com
License: Apache License 2.0
Platform: UNKNOWN
Requires-Python: >=3
